[{"pk": 1, "model": "leave.leaverequest", "fields": {"requester": 4, "day_start": "2008-08-07", "reason": "", "day_end": "2008-08-07", "reason_denial": "", "date": "2008-08-07 03:23:57", "type": "Vacation"}}, {"pk": 1, "model": "leave.manager", "fields": {"category": "supervisor", "user": 3, "users": [3, 4, 5, 6, 7, 8, 9]}}, {"pk": 2, "model": "leave.manager", "fields": {"category": "secretary", "user": 9, "users": [1, 3, 4, 5, 8]}}, {"pk": 3, "model": "leave.manager", "fields": {"category": "secretary", "user": 8, "users": [6, 7, 9]}}, {"pk": 1, "model": "leave.account", "fields": {"category": "vacations", "user": 3, "days": 10}}, {"pk": 2, "model": "leave.account", "fields": {"category": "vacations", "user": 4, "days": 10}}, {"pk": 3, "model": "leave.account", "fields": {"category": "vacations", "user": 5, "days": 10}}, {"pk": 4, "model": "leave.account", "fields": {"category": "vacations", "user": 6, "days": 10}}, {"pk": 5, "model": "leave.account", "fields": {"category": "vacations", "user": 7, "days": 10}}, {"pk": 6, "model": "leave.account", "fields": {"category": "vacations", "user": 8, "days": 10}}, {"pk": 7, "model": "leave.account", "fields": {"category": "vacations", "user": 9, "days": 10}}, {"pk": 12, "model": "leave.account", "fields": {"category": "vacations", "user": 1, "days": 10}}, {"pk": 4, "model": "auth.user", "fields": {"username": "primus", "first_name": "", "last_name": "", "is_active": true, "is_superuser": false, "is_staff": true, "last_login": "2008-08-07 03:24:24", "groups": [3, 4], "user_permissions": [], "password": "sha1$9fdf4$c44f36db2ee5a42733bc166d139b5778b08cf33e", "email": "goflow@alwaysdata.net", "date_joined": "2007-07-28 12:54:36"}}, {"pk": 3, "model": "auth.user", "fields": {"username": "prefectus", "first_name": "", "last_name": "", "is_active": true, "is_superuser": false, "is_staff": true, "last_login": "2008-08-07 03:23:51", "groups": [1, 3, 4], "user_permissions": [], "password": "sha1$42fea$803a874263ca061267131d93930793534307d4c9", "email": "", "date_joined": "2007-07-28 12:52:55"}}, {"pk": 5, "model": "auth.user", "fields": {"username": "secundus", "first_name": "", "last_name": "", "is_active": true, "is_superuser": false, "is_staff": true, "last_login": "2008-04-02 11:00:09", "groups": [3, 4], "user_permissions": [], "password": "sha1$59ac7$aeccc71edac9b47380036dd9f19c9383af68d557", "email": "", "date_joined": "2007-07-29 12:21:50"}}, {"pk": 6, "model": "auth.user", "fields": {"username": "tertius", "first_name": "", "last_name": "", "is_active": true, "is_superuser": false, "is_staff": true, "last_login": "2008-04-01 22:45:23", "groups": [3, 4], "user_permissions": [], "password": "sha1$7b269$cf1cfba01895fafd79473501180c0ee8b643ec60", "email": "", "date_joined": "2007-07-29 12:22:32"}}, {"pk": 7, "model": "auth.user", "fields": {"username": "quartus", "first_name": "", "last_name": "", "is_active": true, "is_superuser": false, "is_staff": true, "last_login": "2008-04-01 22:45:24", "groups": [3, 4], "user_permissions": [], "password": "sha1$15876$c4a36805344668f49614c3720acea5d4a055b0b2", "email": "", "date_joined": "2007-07-29 12:22:56"}}, {"pk": 8, "model": "auth.user", "fields": {"username": "socius", "first_name": "", "last_name": "", "is_active": true, "is_superuser": false, "is_staff": true, "last_login": "2008-04-02 11:00:07", "groups": [2, 3, 4], "user_permissions": [], "password": "sha1$4150a$5126afea8fb33a1735de3d1afc3dd1bfb2b9f1e4", "email": "", "date_joined": "2007-07-29 12:23:20"}}, {"pk": 9, "model": "auth.user", "fields": {"username": "notarius", "first_name": "", "last_name": "", "is_active": true, "is_superuser": false, "is_staff": true, "last_login": "2008-08-07 03:24:09", "groups": [2, 3, 4], "user_permissions": [], "password": "sha1$21f27$9bf9ace1d52ad4c74d199ba76bf711bd8fe74484", "email": "", "date_joined": "2007-07-29 12:24:05"}}, {"pk": 1, "model": "auth.user", "fields": {"username": "admin", "first_name": "", "last_name": "", "is_active": true, "is_superuser": true, "is_staff": true, "last_login": "2008-07-16 18:21:34", "groups": [], "user_permissions": [], "password": "sha1$c5ef3$1ffce0c6ab8bfbd1e56109cd8c32c07487eb8099", "email": "goflow@alwaysdata.net", "date_joined": "2007-07-22 12:28:10"}}]